odoo/addons/dbfilter_from_header/README.rst
odoo/addons/dbfilter_from_header/__init__.py
odoo/addons/dbfilter_from_header/__manifest__.py
odoo/addons/dbfilter_from_header/override.py
odoo/addons/dbfilter_from_header/i18n/dbfilter_from_header.pot
odoo/addons/dbfilter_from_header/i18n/es_AR.po
odoo/addons/dbfilter_from_header/i18n/it.po
odoo/addons/dbfilter_from_header/i18n/zh_CN.po
odoo/addons/dbfilter_from_header/readme/CONFIGURE.md
odoo/addons/dbfilter_from_header/readme/CONTRIBUTORS.md
odoo/addons/dbfilter_from_header/readme/DESCRIPTION.md
odoo/addons/dbfilter_from_header/readme/INSTALL.md
odoo/addons/dbfilter_from_header/readme/USAGE.md
odoo/addons/dbfilter_from_header/static/description/icon.png
odoo/addons/dbfilter_from_header/static/description/index.html
odoo_addon_dbfilter_from_header-18.0.1.0.0.3.dist-info/METADATA
odoo_addon_dbfilter_from_header-18.0.1.0.0.3.dist-info/WHEEL
odoo_addon_dbfilter_from_header-18.0.1.0.0.3.dist-info/top_level.txt
odoo_addon_dbfilter_from_header-18.0.1.0.0.3.dist-info/RECORD
