Metadata-Version: 2.1
Name: odoo-addon-dbfilter_from_header
Version: 18.0.1.0.0.3
Requires-Python: >=3.10
Requires-Dist: odoo==18.0.*
Summary: Filter databases with HTTP headers
Home-page: https://github.com/OCA/server-tools
License: AGPL-3
Author: Therp BV, Odoo Community Association (OCA)
Author-email: support@odoo-community.org
Classifier: Programming Language :: Python
Classifier: Framework :: Odoo
Classifier: Framework :: Odoo :: 18.0
Classifier: License :: OSI Approved :: GNU Affero General Public License v3
